azureml/__init__.py
azureml/train/__init__.py
azureml/train/restclients/__init__.py
azureml/train/restclients/hyperdrive/__init__.py
azureml/train/restclients/hyperdrive/rest_client.py
azureml/train/restclients/hyperdrive/version.py
azureml/train/restclients/hyperdrive/models/__init__.py
azureml/train/restclients/hyperdrive/models/cancel_experiment_respose_dto.py
azureml/train/restclients/hyperdrive/models/create_experiment_dto.py
azureml/train/restclients/hyperdrive/models/create_experiment_dto_generator_config.py
azureml/train/restclients/hyperdrive/models/create_experiment_dto_policy_config.py
azureml/train/restclients/hyperdrive/models/create_experiment_dto_primary_metric_config.py
azureml/train/restclients/hyperdrive/models/error_response.py
azureml/train/restclients/hyperdrive/models/experiment_dto.py
azureml/train/restclients/hyperdrive/models/experiment_dto_generator_config.py
azureml/train/restclients/hyperdrive/models/experiment_dto_policy_config.py
azureml/train/restclients/hyperdrive/models/experiment_dto_primary_metric_config.py
azureml/train/restclients/hyperdrive/models/experiment_response_dto.py
azureml/train/restclients/hyperdrive/models/run_key.py
azureml/train/restclients/hyperdrive/models/run_scope.py
azureml_train_restclients_hyperdrive-1.60.0.dist-info/licenses/LICENSE.txt
azureml_train_restclients_hyperdrive-1.60.0.dist-info/METADATA
azureml_train_restclients_hyperdrive-1.60.0.dist-info/WHEEL
azureml_train_restclients_hyperdrive-1.60.0.dist-info/top_level.txt
azureml_train_restclients_hyperdrive-1.60.0.dist-info/RECORD
